pyrpoc/main.py
pyrpoc/helpers/calibration.py
pyrpoc/helpers/galvo_funcs.py
pyrpoc/helpers/run_image_2d.py
pyrpoc/helpers/utils.py
pyrpoc/helpers/widgets.py
pyrpoc/helpers/zaber.py
pyrpoc/helpers/prior_stage/functions.py
pyrpoc/helpers/prior_stage/prior_interface.py
pyrpoc/mains/acquisition.py
pyrpoc/mains/display.py
pyrpoc/mains/gui.py
pyrpoc/mains/pyqt_rpoc.py
pyrpoc/misc/simulations/organelle_crosstalk.py
pyrpoc/misc/test_scripts/calib_galvos.py
pyrpoc/misc/test_scripts/fake_spt.py
pyrpoc/misc/test_scripts/second_lti.py
pyrpoc/misc/test_scripts/send_sine.py
pyrpoc/misc/test_scripts/send_spiral.py
pyrpoc-0.2.0.dist-info/licenses/LICENSE
pyrpoc-0.2.0.dist-info/METADATA
pyrpoc-0.2.0.dist-info/WHEEL
pyrpoc-0.2.0.dist-info/entry_points.txt
pyrpoc-0.2.0.dist-info/top_level.txt
pyrpoc-0.2.0.dist-info/RECORD
