Metadata-Version: 2.4
Name: pyrpoc
Version: 0.2.0
Summary: Real-time Precision Opto-Control Toolkit
Author-email: Ishaan Singh <sing1125@purdue.com>
License: Copyright 2025, Ishaan Singh
Requires-Python: >=3.8
License-File: LICENSE
Requires-Dist: numpy
Requires-Dist: scipy
Requires-Dist: opencv-python
Requires-Dist: pillow
Requires-Dist: matplotlib
Requires-Dist: pyqt5
Requires-Dist: superqt
Requires-Dist: cellpose
Requires-Dist: nidaqmx
Requires-Dist: pyvisa
Requires-Dist: zaber_motion
Dynamic: license-file
